azureml/__init__.py
azureml/explain/__init__.py
azureml/explain/model/__init__.py
azureml/explain/model/_internal/__init__.py
azureml/explain/model/_internal/explanation_client/__init__.py
azureml/explain/model/common/__init__.py
azureml/explain/model/common/aggregate/__init__.py
azureml/explain/model/common/base_explainer/__init__.py
azureml/explain/model/common/blackbox_explainer/__init__.py
azureml/explain/model/common/chained_identity/__init__.py
azureml/explain/model/common/constants/__init__.py
azureml/explain/model/common/explanation_utils/__init__.py
azureml/explain/model/common/metrics/__init__.py
azureml/explain/model/common/model_summary/__init__.py
azureml/explain/model/common/model_wrapper/__init__.py
azureml/explain/model/common/policy/__init__.py
azureml/explain/model/common/progress/__init__.py
azureml/explain/model/common/storage_policy/__init__.py
azureml/explain/model/common/structured_model_explainer/__init__.py
azureml/explain/model/dataset/__init__.py
azureml/explain/model/dataset/dataset_wrapper/__init__.py
azureml/explain/model/dataset/decorator/__init__.py
azureml/explain/model/explanation/__init__.py
azureml/explain/model/explanation/explanation/__init__.py
azureml/explain/model/mimic/__init__.py
azureml/explain/model/mimic/mimic_explainer/__init__.py
azureml/explain/model/mimic/models/__init__.py
azureml/explain/model/mimic/models/explainable_model/__init__.py
azureml/explain/model/mimic/models/lightgbm_model/__init__.py
azureml/explain/model/mimic/models/linear_model/__init__.py
azureml/explain/model/mimic/models/tree_model/__init__.py
azureml/explain/model/mimic_wrapper/__init__.py
azureml/explain/model/permutation/__init__.py
azureml/explain/model/permutation/metric_constants/__init__.py
azureml/explain/model/permutation/permutation_importance/__init__.py
azureml/explain/model/scoring/__init__.py
azureml/explain/model/scoring/scoring_explainer/__init__.py
azureml/explain/model/shap/__init__.py
azureml_explain_model-1.60.0.dist-info/licenses/LICENSE.txt
azureml_explain_model-1.60.0.dist-info/METADATA
azureml_explain_model-1.60.0.dist-info/WHEEL
azureml_explain_model-1.60.0.dist-info/top_level.txt
azureml_explain_model-1.60.0.dist-info/RECORD
