Metadata-Version: 2.4
Name: azureml-explain-model
Version: 1.60.0
Summary: The package has been deprecated and might not receive future updates.
Home-page: https://docs.microsoft.com/python/api/overview/azure/ml/?view=azure-ml-py
Author: Microsoft Corp
License: https://aka.ms/azureml-sdk-license
Classifier: Development Status :: 5 - Production/Stable
Classifier: Intended Audience :: Developers
Classifier: Intended Audience :: Science/Research
Classifier: License :: Other/Proprietary License
Classifier: Programming Language :: Python :: 3
Classifier: Programming Language :: Python :: 3.6
Classifier: Programming Language :: Python :: 3.7
Classifier: Programming Language :: Python :: 3.8
Classifier: Programming Language :: Python :: 3.9
Classifier: Programming Language :: Python :: 3.10
Classifier: Programming Language :: Python :: 3.11
Classifier: Topic :: Scientific/Engineering :: Artificial Intelligence
Classifier: Operating System :: Microsoft :: Windows
Classifier: Operating System :: MacOS
Classifier: Operating System :: POSIX :: Linux
License-File: LICENSE.txt
Requires-Dist: azureml-interpret~=1.60.0
Provides-Extra: sample
Requires-Dist: azureml-interpret[sample]; extra == "sample"
Provides-Extra: deep
Requires-Dist: azureml-interpret[deep]; extra == "deep"
Provides-Extra: mimic
Requires-Dist: azureml-interpret[mimic]; extra == "mimic"
Dynamic: author
Dynamic: classifier
Dynamic: description
Dynamic: description-content-type
Dynamic: home-page
Dynamic: license
Dynamic: license-file
Dynamic: provides-extra
Dynamic: requires-dist
Dynamic: summary
